xverify/__init__.py
xverify/env.py
xverify/py.typed
xverify/tool_use.py
xverify/tools/__init__.py
xverify/tools/tools.py
xverify/trainers/grpo.py
xverify/utils/logging_utils.py
xverify/xml/__init__.py
xverify/xml/grammar.py
xverify/xml/parser.py
xverify-0.1.0.dist-info/METADATA
xverify-0.1.0.dist-info/WHEEL
xverify-0.1.0.dist-info/RECORD
