Metadata-Version: 2.4
Name: xverify
Version: 0.1.0
Summary: Add your description here
Project-URL: Homepage, https://github.com/tom-pollak/xverify
Project-URL: Repository, https://github.com/tom-pollak/xverify
Project-URL: Issues, https://github.com/tom-pollak/xverify/issues
Author-email: Tom Pollak <tompollak1000@gmail.com>
Requires-Python: >=3.11
Requires-Dist: docstring-parser>=0.16
Requires-Dist: fastcore>=1.7.29
Requires-Dist: pydantic>=2.10.6
Requires-Dist: trl
Requires-Dist: vllm>=0.7.3
Requires-Dist: wandb>=0.19.8
Requires-Dist: xmltodict>=0.14.2
Provides-Extra: tools
Requires-Dist: duckduckgo-search>=7.5.1; extra == 'tools'
